ZypeSDK/__init__.py
ZypeSDK-1.6.dist-info/METADATA
ZypeSDK-1.6.dist-info/WHEEL
ZypeSDK-1.6.dist-info/entry_points.txt
ZypeSDK-1.6.dist-info/top_level.txt
ZypeSDK-1.6.dist-info/RECORD
