Metadata-Version: 2.1
Name: ZypeSDK
Version: 1.6
Summary: Zype Language SDK
Home-page: https://github.com/Zype-Z/ZypeLang
Author: TechGeeks
Author-email: ZypeSDK@tgeeks.cf
Maintainer: Rajdeep Malakar
Maintainer-email: Rajdeep@tgeeks.cf
License: UNKNOWN
Platform: UNKNOWN
Classifier: Programming Language :: Python :: 3
Classifier: License :: OSI Approved :: MIT License
Classifier: Operating System :: OS Independent
Requires-Python: >=3.6
